[
  {
    "nome": "Dashboard",
    "titulo": "Dashboard",
    "elementos": [
      {
        "tipo": "divisor",
        "nome": "ResumoDia",
        "propriedades": [
          {
            "chave": "rotulo",
            "valor": "Resumo do dia"
          }
        ]
      },
      {
        "tipo": "cartao",
        "nome": "TotalVendas",
        "propriedades": [
          {
            "chave": "titulo",
            "valor": "Total de Vendas"
          },
          {
            "chave": "conteudo",
            "valor": "@soma:Venda:total"
          },
          {
            "chave": "variante",
            "valor": "sucesso"
          }
        ]
      },
      {
        "tipo": "cartao",
        "nome": "TotalProdutos",
        "propriedades": [
          {
            "chave": "titulo",
            "valor": "Produtos Cadastrados"
          },
          {
            "chave": "conteudo",
            "valor": "@contagem:Produto"
          },
          {
            "chave": "variante",
            "valor": "info"
          }
        ]
      },
      {
        "tipo": "cartao",
        "nome": "TotalClientes",
        "propriedades": [
          {
            "chave": "titulo",
            "valor": "Clientes Ativos"
          },
          {
            "chave": "conteudo",
            "valor": "@contagem:Cliente"
          },
          {
            "chave": "variante",
            "valor": "primario"
          }
        ]
      },
      {
        "tipo": "cartao",
        "nome": "TicketMedio",
        "propriedades": [
          {
            "chave": "titulo",
            "valor": "Ticket Médio"
          },
          {
            "chave": "conteudo",
            "valor": "@media:Venda:total"
          },
          {
            "chave": "variante",
            "valor": "aviso"
          }
        ]
      },
      {
        "tipo": "divisor",
        "nome": "GraficosDiv",
        "propriedades": [
          {
            "chave": "rotulo",
            "valor": "Análise visual"
          }
        ]
      },
      {
        "tipo": "grafico",
        "nome": "VendasSemana",
        "propriedades": [
          {
            "chave": "tipo",
            "valor": "barras"
          },
          {
            "chave": "entidade",
            "valor": "Venda"
          },
          {
            "chave": "eixoX",
            "valor": "criadaEm"
          },
          {
            "chave": "eixoY",
            "valor": "total"
          }
        ]
      },
      {
        "tipo": "grafico",
        "nome": "DistribuicaoVendas",
        "propriedades": [
          {
            "chave": "tipo",
            "valor": "pizza"
          },
          {
            "chave": "entidade",
            "valor": "Venda"
          },
          {
            "chave": "eixoX",
            "valor": "status"
          },
          {
            "chave": "eixoY",
            "valor": "total"
          }
        ]
      }
    ]
  },
  {
    "nome": "TelaProdutos",
    "titulo": "Produtos",
    "elementos": [
      {
        "tipo": "toolbar",
        "nome": "AcoesProdutos",
        "propriedades": [
          {
            "chave": "botao",
            "valor": "Novo Produto|novoProduto|mais|primario"
          },
          {
            "chave": "botao",
            "valor": "Exportar|exportarCSV|compartilhar|secundario"
          }
        ]
      },
      {
        "tipo": "tabela",
        "nome": "ListaProdutos",
        "propriedades": [
          {
            "chave": "entidade",
            "valor": "Produto"
          },
          {
            "chave": "colunas",
            "valor": [
              {
                "campo": "nome",
                "tipo": "texto"
              },
              {
                "campo": "preco",
                "tipo": "moeda"
              },
              {
                "campo": "estoque",
                "tipo": "numero"
              },
              {
                "campo": "estoqueMinimo",
                "tipo": "numero"
              },
              {
                "campo": "ativo",
                "tipo": "booleano"
              }
            ]
          },
          {
            "chave": "filtravel",
            "valor": "verdadeiro"
          },
          {
            "chave": "ordenavel",
            "valor": "verdadeiro"
          },
          {
            "chave": "paginacao",
            "valor": "20"
          },
          {
            "chave": "acoes",
            "valor": [
              "editar",
              "excluir"
            ]
          }
        ]
      }
    ]
  },
  {
    "nome": "TelaClientes",
    "titulo": "Clientes",
    "elementos": [
      {
        "tipo": "toolbar",
        "nome": "AcoesClientes",
        "propriedades": [
          {
            "chave": "botao",
            "valor": "Novo Cliente|novoCliente|mais|primario"
          }
        ]
      },
      {
        "tipo": "tabela",
        "nome": "ListaClientes",
        "propriedades": [
          {
            "chave": "entidade",
            "valor": "Cliente"
          },
          {
            "chave": "colunas",
            "valor": [
              {
                "campo": "nome",
                "tipo": "texto"
              },
              {
                "campo": "email",
                "tipo": "texto"
              },
              {
                "campo": "telefone",
                "tipo": "texto"
              },
              {
                "campo": "cidade",
                "tipo": "texto"
              },
              {
                "campo": "ativo",
                "tipo": "booleano"
              }
            ]
          },
          {
            "chave": "filtravel",
            "valor": "verdadeiro"
          },
          {
            "chave": "ordenavel",
            "valor": "verdadeiro"
          },
          {
            "chave": "paginacao",
            "valor": "20"
          },
          {
            "chave": "acoes",
            "valor": [
              "editar",
              "excluir"
            ]
          }
        ]
      }
    ]
  },
  {
    "nome": "TelaVendas",
    "titulo": "Vendas",
    "elementos": [
      {
        "tipo": "toolbar",
        "nome": "AcoesVendas",
        "propriedades": [
          {
            "chave": "botao",
            "valor": "Nova Venda|novaVenda|mais|primario"
          },
          {
            "chave": "botao",
            "valor": "Exportar CSV|exportarCSV|compartilhar|secundario"
          }
        ]
      },
      {
        "tipo": "divisor",
        "nome": "ResumoMes",
        "propriedades": [
          {
            "chave": "rotulo",
            "valor": "Resumo do mês"
          }
        ]
      },
      {
        "tipo": "cartao",
        "nome": "TotalDoMes",
        "propriedades": [
          {
            "chave": "titulo",
            "valor": "Total do Mês"
          },
          {
            "chave": "conteudo",
            "valor": "@soma:Venda:total"
          },
          {
            "chave": "variante",
            "valor": "sucesso"
          }
        ]
      },
      {
        "tipo": "cartao",
        "nome": "TicketMedioVendas",
        "propriedades": [
          {
            "chave": "titulo",
            "valor": "Ticket Médio"
          },
          {
            "chave": "conteudo",
            "valor": "@media:Venda:total"
          },
          {
            "chave": "variante",
            "valor": "info"
          }
        ]
      },
      {
        "tipo": "grafico",
        "nome": "GraficoVendas",
        "propriedades": [
          {
            "chave": "tipo",
            "valor": "linha"
          },
          {
            "chave": "entidade",
            "valor": "Venda"
          },
          {
            "chave": "eixoX",
            "valor": "criadaEm"
          },
          {
            "chave": "eixoY",
            "valor": "total"
          }
        ]
      },
      {
        "tipo": "tabela",
        "nome": "TabelaVendas",
        "propriedades": [
          {
            "chave": "entidade",
            "valor": "Venda"
          },
          {
            "chave": "colunas",
            "valor": [
              {
                "campo": "clienteNome",
                "tipo": "texto"
              },
              {
                "campo": "total",
                "tipo": "moeda"
              },
              {
                "campo": "status",
                "tipo": "texto"
              },
              {
                "campo": "criadaEm",
                "tipo": "data"
              }
            ]
          },
          {
            "chave": "filtravel",
            "valor": "verdadeiro"
          },
          {
            "chave": "ordenavel",
            "valor": "verdadeiro"
          },
          {
            "chave": "paginacao",
            "valor": "20"
          },
          {
            "chave": "acoes",
            "valor": [
              "editar",
              "excluir"
            ]
          }
        ]
      }
    ]
  },
  {
    "nome": "App",
    "titulo": "ERP Demo",
    "elementos": [
      {
        "tipo": "gaveta",
        "nome": "MenuPrincipal",
        "propriedades": [
          {
            "chave": "item",
            "valor": "Dashboard|casa|Dashboard"
          },
          {
            "chave": "item",
            "valor": "Produtos|caixa|TelaProdutos"
          },
          {
            "chave": "item",
            "valor": "Clientes|usuarios|TelaClientes"
          },
          {
            "chave": "item",
            "valor": "Vendas|moeda|TelaVendas"
          }
        ]
      }
    ]
  }
]